jodspcc/__init__.py
jodspcc-0.0.1.dist-info/Licence.txt.txt
jodspcc-0.0.1.dist-info/METADATA
jodspcc-0.0.1.dist-info/WHEEL
jodspcc-0.0.1.dist-info/top_level.txt
jodspcc-0.0.1.dist-info/RECORD
