Metadata-Version: 2.1
Name: jodspcc
Version: 0.0.1
Summary: SPCC Codes
Author: Godfather
License: UNKNOWN
Platform: UNKNOWN
License-File: Licence.txt.txt
